MANIFEST.in
README.md
setup.cfg
setup.py
requirements/requirements.txt
tests/__init__.py
tests/test_api.py
tests/test_cli.py
tests/test_objects.py
tests/test_raw_api.py
tests/test_utils.py
vxcube_api/__init__.py
vxcube_api/__main__.py
vxcube_api/api.py
vxcube_api/cli_helpers.py
vxcube_api/errors.py
vxcube_api/objects.py
vxcube_api/raw_api.py
vxcube_api/utils.py
vxcube_api/version.py
vxcube_api.egg-info/PKG-INFO
vxcube_api.egg-info/SOURCES.txt
vxcube_api.egg-info/dependency_links.txt
vxcube_api.egg-info/entry_points.txt
vxcube_api.egg-info/requires.txt
vxcube_api.egg-info/top_level.txt