Metadata-Version: 2.1
Name: vxcube-api
Version: 1.0.4
Summary: Dr.Web vxCube API Client
Home-page: https://www.drweb.com/
Author: Doctor Web
License: Dr.Web
Project-URL: Code, https://github.com/DoctorWebLtd/vxcube-api
Project-URL: Issue tracker, https://github.com/DoctorWebLtd/vxcube-api/issues
Platform: UNKNOWN
Classifier: Operating System :: OS Independent
Classifier: Programming Language :: Python
Classifier: Programming Language :: Python :: 2
Classifier: Programming Language :: Python :: 2.7
Classifier: Programming Language :: Python :: 3
Classifier: Programming Language :: Python :: 3.5
Classifier: Programming Language :: Python :: 3.6
Classifier: Programming Language :: Python :: 3.7
Requires-Python: >=2.7,!=3.0.*,!=3.1.*,!=3.2.*,!=3.3.*,!=3.4.*
